scpygen/__init__.py
scpygen/cli.py
scpygen/generation/generate_flask_api.py
scpygen/generation/generate_flask_full.py
scpygen-1.2.1.dist-info/licenses/LICENSE
scpygen-1.2.1.dist-info/METADATA
scpygen-1.2.1.dist-info/WHEEL
scpygen-1.2.1.dist-info/entry_points.txt
scpygen-1.2.1.dist-info/top_level.txt
scpygen-1.2.1.dist-info/RECORD
