Metadata-Version: 2.4
Name: scpygen
Version: 1.2.1
Summary: A python project structure generator
Requires-Python: >=3.7
License-File: LICENSE
Dynamic: license-file
